boardex_salesforce/__init__.py
boardex_salesforce/config.py
boardex_salesforce/download_ContactDetails_from_sf.py
boardex_salesforce/download_UserDetails_from_sf.py
boardex_salesforce/download_company_from_sf.py
boardex_salesforce/download_contact_from_sf.py
boardex_salesforce/run_daily.py
boardex_salesforce/run_monthly.py
boardex_salesforce/upload_to_salesforce.py
boardex_salesforce/classes/__init__.py
boardex_salesforce/classes/class_bx_sftp.py
boardex_salesforce/classes/class_csv.py
boardex_salesforce/classes/class_download_salesforce.py
boardex_salesforce/classes/class_upload_to_salesforce.py
boardex_salesforce/classes/global_var.py
boardex_salesforce/tests/__init__.py
boardex_salesforce/tests/test_connection.py
boardex_salesforce-0.0.2.dist-info/LICENSE
boardex_salesforce-0.0.2.dist-info/METADATA
boardex_salesforce-0.0.2.dist-info/WHEEL
boardex_salesforce-0.0.2.dist-info/top_level.txt
boardex_salesforce-0.0.2.dist-info/RECORD
