Metadata-Version: 2.1
Name: boardex-salesforce
Version: 0.0.2
Summary: Downloads and Uploads to SalesForce from BoardEx stfp
Home-page: https://aws-bxtfs01.global.root/tfs/BoardExCollection/PTS/_git/Salesforce%20Integration
Author: BoardEx PTS
Author-email: helpdesk@boardex.com
License: MIT
Platform: UNKNOWN
Classifier: Programming Language :: Python :: 3
Classifier: License :: OSI Approved :: MIT License
Classifier: Operating System :: OS Independent
Requires-Python: >=3.5
Requires-Dist: simple-salesforce (==1.10.1)
Requires-Dist: pandas
Requires-Dist: pysftp (==0.2.8)
Requires-Dist: tqdm (==4.48.0)
Requires-Dist: pytest (==6.0.1)
